{
  "requestsFinished": 0,
  "requestsFailed": 0,
  "requestsRetries": 0,
  "requestsFailedPerMinute": 0,
  "requestsFinishedPerMinute": 0,
  "requestMinDurationMillis": null,
  "requestMaxDurationMillis": 0,
  "requestTotalFailedDurationMillis": 0,
  "requestTotalFinishedDurationMillis": 0,
  "crawlerStartedAt": "2026-05-03T18:39:11.410Z",
  "crawlerFinishedAt": "2026-05-03T18:39:12.665Z",
  "statsPersistedAt": "2026-05-03T18:39:12.665Z",
  "crawlerRuntimeMillis": 1589,
  "crawlerLastStartTimestamp": 1777833551076,
  "requestRetryHistogram": [],
  "statsId": 0,
  "requestAvgFailedDurationMillis": null,
  "requestAvgFinishedDurationMillis": null,
  "requestTotalDurationMillis": 0,
  "requestsTotal": 0,
  "requestsWithStatusCode": {},
  "errors": {},
  "retryErrors": {}
}